{
"type": "FeatureCollection",
"crs": { "type": "name", "properties": { "name": "urn:ogc:def:crs:EPSG::5937" } },
                                                                                
"features": [
{ "type": "Feature", "properties": { "Item": "Whale Found", "Lat": 48.240830, "Long": -59.713472 }, "geometry": { "type": "Point", "coordinates": [ 5132650.8080771454, -1695656.2692740113 ] } }
]
}